phelp.py
phelp/__init__.py
phelp-0.1.2.dist-info/LICENSE
phelp-0.1.2.dist-info/METADATA
phelp-0.1.2.dist-info/WHEEL
phelp-0.1.2.dist-info/top_level.txt
phelp-0.1.2.dist-info/RECORD
