Metadata-Version: 2.1
Name: phelp
Version: 0.1.2
Summary: helper scripts for managing files
Home-page: https://github.com/mdxprograms/phelp
Author: Josh Waller
Author-email: mdx.programs@gmail.com
License: MIT
Platform: UNKNOWN
Classifier: License :: OSI Approved :: MIT License
Classifier: Programming Language :: Python
Classifier: Programming Language :: Python :: 3
Classifier: Programming Language :: Python :: 3.7
Classifier: Programming Language :: Python :: Implementation :: CPython
Classifier: Programming Language :: Python :: Implementation :: PyPy
Requires-Python: >=3.7
Requires-Dist: click
